wagtail_bynder/__init__.py
wagtail_bynder/__version__.py
wagtail_bynder/apps.py
wagtail_bynder/blocks.py
wagtail_bynder/exceptions.py
wagtail_bynder/middleware.py
wagtail_bynder/models.py
wagtail_bynder/utils.py
wagtail_bynder/wagtail_hooks.py
wagtail_bynder/widgets.py
wagtail_bynder/management/commands/base.py
wagtail_bynder/management/commands/refresh_bynder_documents.py
wagtail_bynder/management/commands/refresh_bynder_images.py
wagtail_bynder/management/commands/refresh_bynder_videos.py
wagtail_bynder/management/commands/update_stale_documents.py
wagtail_bynder/management/commands/update_stale_images.py
wagtail_bynder/management/commands/update_stale_videos.py
wagtail_bynder/static/bynder/js/compactview-v4.0.0.js
wagtail_bynder/static/bynder/js/video-chooser-modal.js
wagtail_bynder/static/bynder/js/video-chooser-telepath.js
wagtail_bynder/static/bynder/js/video-chooser.js
wagtail_bynder/static/wagtailadmin/js/chooser-modal-handler-factory.js
wagtail_bynder/static/wagtaildocs/js/document-chooser-modal.js
wagtail_bynder/static/wagtailimages/js/image-chooser-modal.js
wagtail_bynder/templates/wagtailadmin/admin_base.html
wagtail_bynder/templates/wagtailadmin/chooser/chooser-bynder.html
wagtail_bynder/templatetags/__init__.py
wagtail_bynder/templatetags/bynder_tags.py
wagtail_bynder/views/__init__.py
wagtail_bynder/views/document.py
wagtail_bynder/views/image.py
wagtail_bynder/views/mixins.py
wagtail_bynder/views/video.py
wagtail_bynder-0.8.1.dist-info/licenses/LICENSE
wagtail_bynder-0.8.1.dist-info/WHEEL
wagtail_bynder-0.8.1.dist-info/METADATA
wagtail_bynder-0.8.1.dist-info/RECORD
