Metadata-Version: 2.4
Name: wagtail-bynder
Version: 0.8.1
Summary: Wagtail integration with Bynder, a Digital Asset Management System
Keywords: Wagtail,Django,Bynder,DAMS,digital asset management
Author-email: Andy Babic  <andy.babic@torchbox.com>
Maintainer-email: Andy Babic <andy.babic@torchbox.com>, Dan Braghis <dan.braghis@torchbox.com>
Requires-Python: >=3.11
Classifier: Development Status :: 3 - Alpha
Classifier: Intended Audience :: Developers
Classifier: License :: OSI Approved :: BSD License
Classifier: Operating System :: OS Independent
Classifier: Programming Language :: Python
Classifier: Programming Language :: Python :: 3
Classifier: Programming Language :: Python :: 3.11
Classifier: Programming Language :: Python :: 3.12
Classifier: Framework :: Django
Classifier: Framework :: Django :: 4.2
Classifier: Framework :: Django :: 5.0
Classifier: Framework :: Django :: 5.1
Classifier: Framework :: Wagtail
Classifier: Framework :: Wagtail :: 5
Classifier: Framework :: Wagtail :: 6
License-File: LICENSE
Requires-Dist: Django>=4.2
Requires-Dist: Wagtail>=5.2
Requires-Dist: bynder-sdk>=1.1.5,<2.0
Requires-Dist: dj-database-url>=2.1.0,<3.0 ; extra == "testing"
Requires-Dist: wagtail_factories>=4.1.0,<5.0 ; extra == "testing"
Requires-Dist: responses>=0.24,<1 ; extra == "testing"
Requires-Dist: coverage>=7.0,<8.0 ; extra == "testing"
Requires-Dist: freezegun>=1.1,<2 ; extra == "testing"
Project-URL: Changelog, https://github.com/torchbox/wagtail-bynder/blob/main/CHANGELOG.md
Project-URL: Source, https://github.com/torchbox/wagtail-bynder
Provides-Extra: testing
